blog/__init__.py
blog/admin.py
blog/apps.py
blog/models.py
blog/tests.py
blog/urls.py
blog/views.py
blog/migrations/0001_initial.py
blog/migrations/0002_auto_20210806_1706.py
blog/migrations/__init__.py
login/__init__.py
login/admin.py
login/apps.py
login/froms.py
login/models.py
login/tests.py
login/urls.py
login/views.py
login/migrations/0001_initial.py
login/migrations/0002_auto_20210801_1839.py
login/migrations/0003_auto_20210801_1901.py
login/migrations/0004_auto_20210802_1518.py
login/migrations/__init__.py
mysite/__init__.py
mysite/settings.py
mysite/urls.py
mysite/wsgi.py
write/__init__.py
write/admin.py
write/apps.py
write/froms.py
write/models.py
write/tests.py
write/urls.py
write/views.py
write/migrations/__init__.py
django_wangchess33333_blog-0.1.dist-info/LICENSE
django_wangchess33333_blog-0.1.dist-info/METADATA
django_wangchess33333_blog-0.1.dist-info/WHEEL
django_wangchess33333_blog-0.1.dist-info/top_level.txt
django_wangchess33333_blog-0.1.dist-info/RECORD
